z/__init__.py
z/__main__.py
z/__version__.py
z/chem.py
z/metrics.py
z/pandas.py
z/pep.py
z/peptides.py
z/rdkit.py
z/score.py
z/sh.py
z/smi.py
z/text.py
z/utils.py
sci_ztools-0.1.4.dist-info/LICENSE
sci_ztools-0.1.4.dist-info/METADATA
sci_ztools-0.1.4.dist-info/WHEEL
sci_ztools-0.1.4.dist-info/entry_points.txt
sci_ztools-0.1.4.dist-info/top_level.txt
sci_ztools-0.1.4.dist-info/RECORD
