Metadata-Version: 2.1
Name: sci-ztools
Version: 0.1.4
Summary: A Unified Tool Set for Science Researches
Home-page: https://github.com/zhaisilong/z
Author: Zhai Silong
Author-email: zhaisilong@outlook.com
License: MIT
Classifier: Development Status :: 2 - Pre-Alpha
Classifier: License :: OSI Approved :: MIT License
Classifier: Programming Language :: Python :: 3.7
Requires-Python: >=3.6
License-File: LICENSE
Requires-Dist: rich
Requires-Dist: six
Requires-Dist: future
